{
  "metadata": [
  ],
  "build": {
    "content": [
      {
        "files": [
          "Simplic Studio/**.md",
          "Simplic Studio/**/toc.yml",
          "toc.yml",
          "*.md"
        ]
      },
      {
        "files": [
          "DMS/**.md",
          "DMS/**/toc.yml",
          "toc.yml",
          "*.md"
        ]
      },
      {
        "files": [
          "CRM/**.md",
          "CRM/**/toc.yml",
          "toc.yml",
          "*.md"
        ]
      }
    ],
    "resource": [
      {
        "files": [
          "images/**"
        ]
      }
    ],
    "overwrite": [
      {
        "files": [
          
        ],
        "exclude": [
          "obj/**",
          "_site/**"
        ]
      }
    ],
    "dest": "../_site/user/_site",
    "globalMetadataFiles": 
    [
      "globalMetadata.json"
    ],
    "fileMetadataFiles": [],
    "template": [
      "../template/user"
    ],
    "postProcessors": [],
    "noLangKeyword": false,
    "keepFileLink": false,
    "cleanupCacheHistory": false,
    "disableGitFeatures": false
  }
}